ilbuilder/__init__.py
ilbuilder/data.py
ilbuilder/utils.py
ilbuilder/version.py
ilbuilder/builder/__init__.py
ilbuilder/builder/builder.py
ilbuilder-0.1.3.dist-info/licenses/LICENSE.txt
ilbuilder_cli/__init__.py
ilbuilder_cli/add.py
ilbuilder_cli/build.py
ilbuilder_cli/command.py
ilbuilder_cli/data.py
scripts/build.py
scripts/install.py
ilbuilder-0.1.3.dist-info/METADATA
ilbuilder-0.1.3.dist-info/WHEEL
ilbuilder-0.1.3.dist-info/top_level.txt
ilbuilder-0.1.3.dist-info/RECORD
