Metadata-Version: 2.4
Name: ilbuilder
Version: 0.1.3
Summary: python builder
Author-email: ndrzy <dandan0019@outlook.com>
License: MIT
Project-URL: Homepage, https://github.com/meatdumplings0019/ilbuilder
Requires-Python: >=3.10
License-File: LICENSE.txt
Requires-Dist: colorama
Requires-Dist: rushlib
Requires-Dist: rushdata
Requires-Dist: rushrunning
Requires-Dist: pyinstaller
Dynamic: license-file
